StockStalker/__init__.py
StockStalker/crypto.py
StockStalker/currency.py
StockStalker/past.py
StockStalker/present.py
StockStalker/stalker.py
StockStalker/utils.py
StockStalker-0.1.dist-info/LICENSE
StockStalker-0.1.dist-info/METADATA
StockStalker-0.1.dist-info/WHEEL
StockStalker-0.1.dist-info/top_level.txt
StockStalker-0.1.dist-info/RECORD
