Metadata-Version: 2.1
Name: StockStalker
Version: 0.1
Summary: easy to use, robust and quick stocks package
Home-page: https://github.com/RockoonTechnologies/StockStalker
Author: Meepers
Author-email: rockoontech@gmail.com
License: MIT
Platform: UNKNOWN
Requires-Dist: beautifulsoup4 (==4.9.3)
Requires-Dist: pandas (==1.1.5)
Requires-Dist: requests (==2.25.1)
Requires-Dist: lxml (==4.6.2)
Requires-Dist: Munch (==2.5.0)
